miniqc/__init__.py
miniqc/__main__.py
miniqc/_version.py
miniqc/_version.pyi
miniqc/nifti.py
miniqc/py.typed
miniqc/types.py
miniqc-23.1.1.dist-info/METADATA
miniqc-23.1.1.dist-info/WHEEL
miniqc-23.1.1.dist-info/entry_points.txt
miniqc-23.1.1.dist-info/licenses/LICENSE.txt
miniqc-23.1.1.dist-info/RECORD
