Metadata-Version: 2.3
Name: miniqc
Version: 23.1.1
Summary: A BIDS app for performing minimal QC beyond validation
Project-URL: Documentation, https://github.com/OpenNeuroOrg/miniqc#readme
Project-URL: Issues, https://github.com/OpenNeuroOrg/miniqc/issues
Project-URL: Source, https://github.com/OpenNeuroOrg/miniqc
Author-email: Chris Markiewicz <markiewicz@stanford.edu>
License-Expression: MIT
License-File: LICENSE.txt
Classifier: Development Status :: 4 - Beta
Classifier: Operating System :: OS Independent
Classifier: Programming Language :: Python
Classifier: Programming Language :: Python :: 3
Requires-Python: >=3.9
Requires-Dist: nibabel
Requires-Dist: typer
Requires-Dist: typing-extensions
